anysqlite/__init__.py
anysqlite/_core.py
anysqlite/py.typed
anysqlite-0.0.4.dist-info/METADATA
anysqlite-0.0.4.dist-info/WHEEL
anysqlite-0.0.4.dist-info/licenses/LICENSE.txt
anysqlite-0.0.4.dist-info/RECORD
