Metadata-Version: 2.1
Name: anysqlite
Version: 0.0.4
Project-URL: Issues, https://github.com/karosis88/anysqlite/issues
Project-URL: Source, https://github.com/karosis88/anysqlite
Author-email: Karen Petrosyan <kar.petrosyanpy@gmail.com>
License-Expression: BSD-3-Clause
License-File: LICENSE.txt
Classifier: Development Status :: 4 - Beta
Classifier: Programming Language :: Python
Classifier: Programming Language :: Python :: 3.8
Classifier: Programming Language :: Python :: 3.9
Classifier: Programming Language :: Python :: 3.10
Classifier: Programming Language :: Python :: 3.11
Classifier: Programming Language :: Python :: 3.12
Classifier: Programming Language :: Python :: Implementation :: CPython
Classifier: Programming Language :: Python :: Implementation :: PyPy
Requires-Python: >=3.8
Requires-Dist: anyio>3.4.0
